servos/__init__.py
servos/manage.py
servos/contrib/__init__.py
servos/contrib/i18n/__init__.py
servos/contrib/i18n/middle_i18n.py
servos/contrib/i18n/settings.ini
servos/core/__init__.py
servos/core/commands.py
servos/core/default_settings.ini
servos/core/dispatch.py
servos/core/service.py
servos/core/simpleframe.py
servos/i18n/__init__.py
servos/i18n/trans_null.py
servos/i18n/trans_real.py
servos/template_files/command/commands.py
servos/template_files/project/.gitignore.template
servos/template_files/project/manage.py
servos/template_files/project/setup.py
servos/template_files/project/services/__init__.py
servos/template_files/project/services/local_settings.ini
servos/template_files/project/services/settings.ini
servos/template_files/service/__init__.py
servos/template_files/service/requirements.txt
servos/template_files/service/service.py
servos/template_files/service/settings.ini
servos/utils/__init__.py
servos/utils/common.py
servos/utils/localproxy.py
servos/utils/pyini.py
servos_framework-0.0.1.dev6.dist-info/AUTHORS
servos_framework-0.0.1.dev6.dist-info/METADATA
servos_framework-0.0.1.dev6.dist-info/WHEEL
servos_framework-0.0.1.dev6.dist-info/entry_points.txt
servos_framework-0.0.1.dev6.dist-info/pbr.json
servos_framework-0.0.1.dev6.dist-info/top_level.txt
servos_framework-0.0.1.dev6.dist-info/RECORD
